<TextureAtlas imagePath="sprites.png">
	<SubTexture name="body_3Dblue.png" x="450" y="292" width="148" height="82"/>
	<SubTexture name="body_3Dgreen.png" x="150" y="468" width="148" height="82"/>
	<SubTexture name="body_3Dred.png" x="0" y="468" width="148" height="82"/>
	<SubTexture name="body_3Dyellow.png" x="450" y="168" width="148" height="122"/>
	<SubTexture name="body_blue.png" x="450" y="84" width="148" height="82"/>
	<SubTexture name="body_green.png" x="450" y="0" width="148" height="82"/>
	<SubTexture name="body_red.png" x="300" y="436" width="148" height="82"/>
	<SubTexture name="body_yellow.png" x="300" y="312" width="148" height="122"/>
	<SubTexture name="robot_3Dblue.png" x="0" y="156" width="148" height="154"/>
	<SubTexture name="robot_3Dgreen.png" x="0" y="0" width="148" height="154"/>
	<SubTexture name="robot_3Dred.png" x="300" y="156" width="148" height="154"/>
	<SubTexture name="robot_3Dyellow.png" x="300" y="0" width="148" height="154"/>
	<SubTexture name="robot_blue.png" x="150" y="312" width="148" height="154"/>
	<SubTexture name="robot_green.png" x="150" y="156" width="148" height="154"/>
	<SubTexture name="robot_red.png" x="150" y="0" width="148" height="154"/>
	<SubTexture name="robot_yellow.png" x="0" y="312" width="148" height="154"/>
	<SubTexture name="track_long.png" x="300" y="520" width="123" height="54"/>
	<SubTexture name="track_short.png" x="425" y="520" width="107" height="54"/>
</TextureAtlas>